[
  {
    "category": "``ecs``", 
    "description": "[``botocore``] Update ecs client to latest version", 
    "type": "api-change"
  }, 
  {
    "category": "``opsworkscm``", 
    "description": "[``botocore``] Update opsworkscm client to latest version", 
    "type": "api-change"
  }, 
  {
    "category": "``workspaces``", 
    "description": "[``botocore``] Update workspaces client to latest version", 
    "type": "api-change"
  }, 
  {
    "category": "``datasync``", 
    "description": "[``botocore``] Update datasync client to latest version", 
    "type": "api-change"
  }, 
  {
    "category": "``eks``", 
    "description": "[``botocore``] Update eks client to latest version", 
    "type": "api-change"
  }
]