[
  {
    "category": "``apigateway``", 
    "description": "[``botocore``] Update apigateway client to latest version", 
    "type": "api-change"
  }, 
  {
    "category": "``glue``", 
    "description": "[``botocore``] Update glue client to latest version", 
    "type": "api-change"
  }, 
  {
    "category": "``cloudformation``", 
    "description": "[``botocore``] Update cloudformation client to latest version", 
    "type": "api-change"
  }, 
  {
    "category": "``storagegateway``", 
    "description": "[``botocore``] Update storagegateway client to latest version", 
    "type": "api-change"
  }
]